{
	"version": 1,
	"allow_edit": true,
	"plugins": [],
	"panes": [
		{
			"width": 1,
			"row": {
				"3": 1
			},
			"col": {
				"3": 1
			},
			"col_width": 1,
			"widgets": [
				{
					"type": "text_widget",
					"settings": {
						"title": "Source Port",
						"size": "regular",
						"value": "datasources[\"HPotter\"][\"sourcePort\"]",
						"animate": true
					}
				}
			]
		}
	],
	"datasources": [
		{
			"name": "HPotter",
			"type": "JSON",
			"settings": {
				"url": "http://127.0.0.1:8080",
				"use_thingproxy": true,
				"refresh": 5,
				"method": "GET"
			}
		}
	],
	"columns": 3
}
